MANIFEST.in
README.txt
setup.py
docs/HISTORY.txt
horae/__init__.py
horae.sphinx.grok.egg-info/PKG-INFO
horae.sphinx.grok.egg-info/SOURCES.txt
horae.sphinx.grok.egg-info/dependency_links.txt
horae.sphinx.grok.egg-info/entry_points.txt
horae.sphinx.grok.egg-info/namespace_packages.txt
horae.sphinx.grok.egg-info/not-zip-safe
horae.sphinx.grok.egg-info/requires.txt
horae.sphinx.grok.egg-info/top_level.txt
horae/sphinx/__init__.py
horae/sphinx/grok/__init__.py