Metadata-Version: 1.0
Name: horae.sphinx.grok
Version: 1.0a1
Summary: Provides grok specific autodoc directives for sphinx
Home-page: UNKNOWN
Author: Simon Kaeser
Author-email: skaeser@gmail.com
License: GPL
Platform: UNKNOWN
Classifier: Programming Language :: Python
